[
  {
    "id": 1,
    "name": "Margherita Pizza",
    "category": "Pizza",
    "description": "Classic Margherita with fresh tomatoes and mozzarella cheese",
    "price": 300,
    "discountPrice": 250,
    "rating": 4.5,
    "tag": "Bestseller",
    "image": "https://images.pexels.com/photos/708587/pexels-photo-708587.jpeg"
  },
  {
    "id": 2,
    "name": "Pepperoni Pizza",
    "category": "Pizza",
    "description": "Spicy pepperoni with mozzarella cheese",
    "price": 350,
    "discountPrice": 300,
    "rating": 4.7,
    "tag": "Bestseller",
    "image": "https://images.pexels.com/photos/315755/pexels-photo-315755.jpeg"
  },
  {
    "id": 3,
    "name": "Veggie Pizza",
    "category": "Pizza",
    "description": "Loaded with fresh veggies and mozzarella cheese",
    "price": 320,
    "discountPrice": 270,
    "rating": 4.6,
    "tag": "Bestseller",
    "image": "https://images.pexels.com/photos/1435907/pexels-photo-1435907.jpeg"
  },
  {
    "id": 4,
    "name": "BBQ Chicken Pizza",
    "category": "Pizza",
    "description": "BBQ sauce, grilled chicken, and red onions",
    "price": 380,
    "discountPrice": 330,
    "rating": 4.8,
    "tag": "Bestseller",
    "image": "https://images.pexels.com/photos/2619967/pexels-photo-2619967.jpeg"
  },
  {
    "id": 5,
    "name": "Hawaiian Pizza",
    "category": "Pizza",
    "description": "Ham and pineapple with mozzarella cheese",
    "price": 340,
    "discountPrice": 290,
    "rating": 4.4,
    "tag": "Bestseller",
    "image": "https://images.pexels.com/photos/1183098/pexels-photo-1183098.jpeg"
  },
  {
    "id": 6,
    "name": "Mushroom Pizza",
    "category": "Pizza",
    "description": "Fresh mushrooms with mozzarella cheese",
    "price": 310,
    "discountPrice": 260,
    "rating": 4.3,
    "tag": "Bestseller",
    "image": "https://images.pexels.com/photos/1435909/pexels-photo-1435909.jpeg"
  },
  {
    "id": 7,
    "name": "Burger Classic",
    "category": "Burger",
    "description": "Classic beef burger with lettuce and tomato",
    "price": 150,
    "discountPrice": 120,
    "rating": 4.5,
    "tag": "Bestseller",
    "image": "https://images.pexels.com/photos/1639557/pexels-photo-1639557.jpeg"
  },
  {
    "id": 8,
    "name": "Cheese Burger",
    "category": "Burger",
    "description": "Beef burger with cheddar cheese",
    "price": 170,
    "discountPrice": 140,
    "rating": 4.6,
    "tag": "Bestseller",
    "image": "https://images.pexels.com/photos/1639557/pexels-photo-1639557.jpeg"
  },
  {
    "id": 9,
    "name": "Veggie Burger",
    "category": "Burger",
    "description": "Grilled veggie patty with lettuce and tomato",
    "price": 140,
    "discountPrice": 110,
    "rating": 4.4,
    "tag": "Bestseller",
    "image": "https://images.pexels.com/photos/1639557/pexels-photo-1639557.jpeg"
  },
  {
    "id": 10,
    "name": "Chicken Burger",
    "category": "Burger",
    "description": "Grilled chicken breast with lettuce and mayo",
    "price": 160,
    "discountPrice": 130,
    "rating": 4.5,
    "tag": "Bestseller",
    "image": "https://images.pexels.com/photos/1639557/pexels-photo-1639557.jpeg"
  },
  {
    "id": 11,
    "name": "Spicy Dosa",
    "category": "Dosa",
    "description": "Crispy dosa with spicy potato filling",
    "price": 100,
    "discountPrice": 80,
    "rating": 4.7,
    "tag": "Bestseller",
    "image": "https://images.pexels.com/photos/1027607/pexels-photo-1027607.jpeg"
  },
  {
    "id": 12,
    "name": "Masala Dosa",
    "category": "Dosa",
    "description": "Dosa with classic potato filling",
    "price": 90,
    "discountPrice": 70,
    "rating": 4.5,
    "tag": "Bestseller",
    "image": "https://images.pexels.com/photos/1027607/pexels-photo-1027607.jpeg"
  },
  {
    "id": 13,
    "name": "Cheese Dosa",
    "category": "Dosa",
    "description": "Dosa filled with melted cheese",
    "price": 110,
    "discountPrice": 90,
    "rating": 4.6,
    "tag": "Bestseller",
    "image": "https://images.pexels.com/photos/1027607/pexels-photo-1027607.jpeg"
  },
  {
    "id": 14,
    "name": "Paneer Dosa",
    "category": "Dosa",
    "description": "Dosa with paneer filling",
    "price": 120,
    "discountPrice": 100,
    "rating": 4.7,
    "tag": "Bestseller",
    "image": "https://images.pexels.com/photos/1027607/pexels-photo-1027607.jpeg"
  },
  {
    "id": 15,
    "name": "Plain Dosa",
    "category": "Dosa",
    "description": "Classic plain dosa",
    "price": 80,
    "discountPrice": 60,
    "rating": 4.4,
    "tag": "Bestseller",
    "image": "https://images.pexels.com/photos/1027607/pexels-photo-1027607.jpeg"
  },
  {
    "id": 16,
    "name": "Pav Bhaji Classic",
    "category": "Pav Bhaji",
    "description": "Classic pav bhaji with buttered pav",
    "price": 130,
    "discountPrice": 110,
    "rating": 4.5,
    "tag": "Bestseller",
    "image": "https://images.pexels.com/photos/3023469/pexels-photo-3023469.jpeg"
  },
  {
    "id": 17,
    "name": "Cheese Pav Bhaji",
    "category": "Pav Bhaji",
    "description": "Pav bhaji topped with melted cheese",
    "price": 150,
    "discountPrice": 130,
    "rating": 4.7,
    "tag": "Bestseller",
    "image": "https://images.pexels.com/photos/3023469/pexels-photo-3023469.jpeg"
  },
  {
    "id": 18,
    "name": "Paneer Pav Bhaji",
    "category": "Pav Bhaji",
    "description": "Pav bhaji with paneer topping",
    "price": 160,
    "discountPrice": 140,
    "rating": 4.6,
    "tag": "Bestseller",
    "image": "https://images.pexels.com/photos/3023469/pexels-photo-3023469.jpeg"
  },
  {
    "id": 19,
    "name": "Jain Pav Bhaji",
    "category": "Pav Bhaji",
    "description": "No onion, no garlic pav bhaji",
    "price": 140,
    "discountPrice": 120,
    "rating": 4.4,
    "tag": "Bestseller",
    "image": "https://images.pexels.com/photos/3023469/pexels-photo-3023469.jpeg"
  },
  {
    "id": 20,
    "name": "Special Pav Bhaji",
    "category": "Pav Bhaji",
    "description": "Special pav bhaji with extra butter",
    "price": 170,
    "discountPrice": 150,
    "rating": 4.8,
    "tag": "Bestseller",
    "image": "https://images.pexels.com/photos/3023469/pexels-photo-3023469.jpeg"
  },
  {
    "id": 21,
    "name": "Chole Bhature Classic",
    "category": "Chole Bhature",
    "description": "Classic chole served with bhature",
    "price": 150,
    "discountPrice": 130,
    "rating": 4.6,
    "tag": "Bestseller",
    "image": "https://images.pexels.com/photos/7249154/pexels-photo-7249154.jpeg"
  },
  {
    "id": 22,
    "name": "Paneer Chole Bhature",
    "category": "Chole Bhature",
    "description": "Chole served with paneer bhature",
    "price": 170,
    "discountPrice": 150,
    "rating": 4.7,
    "tag": "Bestseller",
    "image": "https://images.pexels.com/photos/7249154/pexels-photo-7249154.jpeg"
  },
  {
    "id": 23,
    "name": "Cheese Chole Bhature",
    "category": "Chole Bhature",
    "description": "Chole served with cheese bhature",
    "price": 160,
    "discountPrice": 140,
    "rating": 4.5,
    "tag": "Bestseller",
    "image": "https://images.pexels.com/photos/7249154/pexels-photo-7249154.jpeg"
  },
  {
    "id": 24,
    "name": "Jain Chole Bhature",
    "category": "Chole Bhature",
    "description": "No onion, no garlic chole bhature",
    "price": 140,
    "discountPrice": 120,
    "rating": 4.4,
    "tag": "Bestseller",
    "image": "https://images.pexels.com/photos/7249154/pexels-photo-7249154.jpeg"
  },
  {
    "id": 25,
    "name": "Special Chole Bhature",
    "category": "Chole Bhature",
    "description": "Special chole bhature with extra butter",
    "price": 180,
    "discountPrice": 160,
    "rating": 4.8,
    "tag": "Bestseller",
    "image": "https://images.pexels.com/photos/7249154/pexels-photo-7249154.jpeg"
  },
  {
    "id": 26,
    "name": "Idli Sambar Classic",
    "category": "Idli Sambar",
    "description": "Classic idli served with sambar and chutney",
    "price": 100,
    "discountPrice": 80,
    "rating": 4.5,
    "tag": "Bestseller",
    "image": "https://images.pexels.com/photos/1893555/pexels-photo-1893555.jpeg"
  },
  {
    "id": 27,
    "name": "Paneer Idli Sambar",
    "category": "Idli Sambar",
    "description": "Idli served with paneer sambar",
    "price": 120,
    "discountPrice": 100,
    "rating": 4.6,
    "tag": "Bestseller",
    "image": "https://images.pexels.com/photos/1893555/pexels-photo-1893555.jpeg"
  },
  {
    "id": 28,
    "name": "Cheese Idli Sambar",
    "category": "Idli Sambar",
    "description": "Idli served with cheese sambar",
    "price": 110,
    "discountPrice": 90,
    "rating": 4.5,
    "tag": "Bestseller",
    "image": "https://images.pexels.com/photos/1893555/pexels-photo-1893555.jpeg"
  },
  {
    "id": 29,
    "name": "Spicy Idli Sambar",
    "category": "Idli Sambar",
    "description": "Spicy idli served with sambar",
    "price": 130,
    "discountPrice": 110,
    "rating": 4.7,
    "tag": "Bestseller",
    "image": "https://images.pexels.com/photos/1893555/pexels-photo-1893555.jpeg"
  },
  {
    "id": 30,
    "name": "Special Idli Sambar",
    "category": "Idli Sambar",
    "description": "Special idli served with sambar and chutney",
    "price": 140,
    "discountPrice": 120,
    "rating": 4.8,
    "tag": "Bestseller",
    "image": "https://images.pexels.com/photos/1893555/pexels-photo-1893555.jpeg"
  },
  {
    "id": 31,
    "name": "Veg Fried Rice",
    "category": "Fried Rice",
    "description": "Vegetable fried rice with soy sauce",
    "price": 120,
    "discountPrice": 100,
    "rating": 4.5,
    "tag": "Bestseller",
    "image": "https://images.pexels.com/photos/1311778/pexels-photo-1311778.jpeg"
  },
  {
    "id": 32,
    "name": "Chicken Fried Rice",
    "category": "Fried Rice",
    "description": "Chicken fried rice with vegetables",
    "price": 140,
    "discountPrice": 120,
    "rating": 4.6,
    "tag": "Bestseller",
    "image": "https://images.pexels.com/photos/1311778/pexels-photo-1311778.jpeg"
  },
  {
    "id": 33,
    "name": "Egg Fried Rice",
    "category": "Fried Rice",
    "description": "Egg fried rice with vegetables",
    "price": 130,
    "discountPrice": 110,
    "rating": 4.5,
    "tag": "Bestseller",
    "image": "https://images.pexels.com/photos/1311778/pexels-photo-1311778.jpeg"
  },
  {
    "id": 34,
    "name": "Paneer Fried Rice",
    "category": "Fried Rice",
    "description": "Paneer fried rice with soy sauce",
    "price": 150,
    "discountPrice": 130,
    "rating": 4.7,
    "tag": "Bestseller",
    "image": "https://images.pexels.com/photos/1311778/pexels-photo-1311778.jpeg"
  },
  {
    "id": 35,
    "name": "Special Fried Rice",
    "category": "Fried Rice",
    "description": "Special fried rice with mixed vegetables",
    "price": 160,
    "discountPrice": 140,
    "rating": 4.8,
    "tag": "Bestseller",
    "image": "https://images.pexels.com/photos/1311778/pexels-photo-1311778.jpeg"
  },
  {
    "id": 36,
    "name": "Butter Chicken",
    "category": "Chicken",
    "description": "Tender chicken cooked in a rich butter sauce",
    "price": 180,
    "discountPrice": 160,
    "rating": 4.8,
    "tag": "Bestseller",
    "image": "https://images.pexels.com/photos/212769/pexels-photo-212769.jpeg"
  },
  {
    "id": 37,
    "name": "Chicken Tikka",
    "category": "Chicken",
    "description": "Grilled chicken tikka with spices",
    "price": 200,
    "discountPrice": 180,
    "rating": 4.7,
    "tag": "Bestseller",
    "image": "https://images.pexels.com/photos/212769/pexels-photo-212769.jpeg"
  },
  {
    "id": 38,
    "name": "Chicken Biryani",
    "category": "Chicken",
    "description": "Fragrant rice with spiced chicken",
    "price": 220,
    "discountPrice": 200,
    "rating": 4.6,
    "tag": "Bestseller",
    "image": "https://images.pexels.com/photos/212769/pexels-photo-212769.jpeg"
  },
  {
    "id": 39,
    "name": "Chicken Korma",
    "category": "Chicken",
    "description": "Chicken cooked in a creamy sauce",
    "price": 190,
    "discountPrice": 170,
    "rating": 4.5,
    "tag": "Bestseller",
    "image": "https://images.pexels.com/photos/212769/pexels-photo-212769.jpeg"
  },
  {
    "id": 40,
    "name": "Chicken Curry",
    "category": "Chicken",
    "description": "Spicy chicken curry with rice",
    "price": 180,
    "discountPrice": 160,
    "rating": 4.4,
    "tag": "Bestseller",
    "image": "https://images.pexels.com/photos/212769/pexels-photo-212769.jpeg"
  }
]
